evmotosentiment/__init__.py
evmotosentiment/clean_message/__init__.py
evmotosentiment/clean_message/general_cleaner.py
evmotosentiment/wsentiment/__init__.py
evmotosentiment/wsentiment/whatsappdataframe.py
evmotosentiment/wsentiment/whatsappsentiment.py
evmotosentiment-0.3.0.dist-info/licenses/LICENSE.txt
evmotosentiment-0.3.0.dist-info/METADATA
evmotosentiment-0.3.0.dist-info/WHEEL
evmotosentiment-0.3.0.dist-info/top_level.txt
evmotosentiment-0.3.0.dist-info/RECORD
