Metadata-Version: 2.4
Name: evmotosentiment
Version: 0.3.0
Summary: Package to analyse Motorcycle EV swap related issues
Author: Ayikwei Richard
License: CC-BY-4.0
Requires-Python: >=3.11
License-File: LICENSE.txt
Requires-Dist: commitizen>=4.8.3
Requires-Dist: nltk>=3.9.1
Requires-Dist: pandas>=2.3.1
Requires-Dist: pyment>=0.3.3
Requires-Dist: pytest>=8.4.1
Requires-Dist: ruff>=0.12.9
Requires-Dist: setuptools>=80.9.0
Requires-Dist: tox>=4.28.4
Requires-Dist: tox-uv>=1.28.0
Dynamic: author
Dynamic: license-file
